{
    "call_number": "Illus. in QB41.G14 Rosenwald Coll. 1350 [Rare Book RR]",
    "collection": [
        "cph",
        "diof",
        "pp"
    ],
    "created": "2016-04-20 00:00:00",
    "created_published_date": "[published 1632]",
    "creator": "Galilei, Galileo, 1564-1642.",
    "image": {
        "alt": "digitized item thumbnail",
        "full": "//www.loc.gov/pictures/cdn/service/pnp/cph/3b40000/3b41000/3b41300/3b41323r.jpg",
        "square": "//cdn.loc.gov/service/pnp/cph/3b40000/3b41000/3b41300/3b41323_75x75px.jpg",
        "thumb": "//cdn.loc.gov/service/pnp/cph/3b40000/3b41000/3b41300/3b41323_150px.jpg"
    },
    "index": 194,
    "links": {
        "item": "//www.loc.gov/pictures/item/92516354/",
        "resource": "//www.loc.gov/pictures/item/92516354/resource/"
    },
    "medium": "1 p.",
    "medium_brief": "1 p.",
    "modified": "2016-04-20 00:00:00",
    "pk": "92516354",
    "reproduction_number": "LC-USZ62-95158 (b&w film copy neg.)",
    "source_created": "1992-09-08 00:00:00",
    "source_modified": "2013-06-17 00:00:00",
    "subjects": [
        "Title pages--1630-1640."
    ],
    "title": "[Title page of Dialogo di Galilei Linceo, with three fish encircled by wreath and banner, probably emblem for printer Giovanni Batista Landini of Florence]"
}