{
    "call_number": "HALS PA-25-19",
    "collection": [
        "diof",
        "hh"
    ],
    "created": "2017-09-28 00:00:00",
    "created_published_date": "2008",
    "creator": "Thomas, Jennifer",
    "image": {
        "alt": "item not digitized thumbnail",
        "full": "//www.loc.gov/pictures/static/images/item/500x500_notdigitized.png",
        "square": "//www.loc.gov/pictures/static/images/item/not_digitized_buttons75X75.png",
        "thumb": "//www.loc.gov/pictures/static/images/item/notdigitized_buttons140X120.png"
    },
    "index": 871,
    "links": {
        "item": "//www.loc.gov/pictures/item/pa4153.photos.19/",
        "resource": null
    },
    "medium": "4 x 5 in.",
    "medium_brief": "4 x 5 in.",
    "modified": "2017-09-28 00:00:00",
    "pk": "pa4153.photos.19",
    "reproduction_number": "HALS PA-25-19",
    "source_created": "1970-01-01 00:00:00",
    "source_modified": "2017-09-28 00:00:00",
    "subjects": null,
    "title": "Rec Hall, west facade. Outside porch/stage added ca. 2003. Flag pole probably of CCC era. Asphalt shingles. Tree groves in background behind building. - Allegheny National Forest, CCC Camp ANF-1 , The camp&#146;s main entrance is located at the intersection of Duhring Road (ANF 131) and ANF 124, Pennsylvania, with the interior site road known as Trail Ride Drive., Marienville, Forest County, PA"
}