{
    "call_number": "Unprocessed [item] [P&P]",
    "collection": [
        "cph",
        "pp"
    ],
    "created": "2016-04-21T00:00:00Z",
    "created_published_date": "[1958]",
    "creator": "Cummings, Michael",
    "image": {
        "alt": "digitized item thumbnail",
        "full": "//www.loc.gov/pictures/cdn/service/pnp/ppmsca/07100/07165_150px.jpg",
        "square": "//cdn.loc.gov/service/pnp/ppmsca/07100/07165_75x75px.jpg",
        "thumb": "//cdn.loc.gov/service/pnp/ppmsca/07100/07165_150px.jpg"
    },
    "index": 92,
    "links": {
        "item": "//www.loc.gov/pictures/item/2004679135/",
        "resource": "//www.loc.gov/pictures/item/2004679135/resource/"
    },
    "medium": "1 drawing : ink brush, blue watercolor, and opaque white over graphite underdrawing ; 21.7 x 31.7 cm (sheet)",
    "medium_brief": "1 drawing :",
    "modified": "2016-04-21T00:00:00Z",
    "pk": "2004679135",
    "reproduction_number": "LC-DIG-ppmsca-07165 (digital file from original drawing)",
    "source_created": "2004-11-10T00:00:00Z",
    "source_modified": "2010-02-17T00:00:00Z",
    "subjects": [
        "Dulles, John Foster,--1888-1959.",
        "MacMillan, Harold,--1894-1986.",
        "Adenauer, Konrad,--1876-1967.",
        "International relations--United States--1950-1960.",
        "Public speaking--1950-1960.",
        "Editorial cartoons--British--1950-1960.",
        "Ink drawings--British--Color--1950-1960."
    ],
    "title": "\"Maybe, I should give myself an agonising re-appraisal ...\""
}